DocumentsReader/DocumentReader.py
DocumentsReader/__init__.py
DocumentsReader/helper.py
DocumentsReader/data/DejaVuSans.ttf
DocumentsReader-1.1.5.dist-info/METADATA
DocumentsReader-1.1.5.dist-info/WHEEL
DocumentsReader-1.1.5.dist-info/top_level.txt
DocumentsReader-1.1.5.dist-info/RECORD
