Metadata-Version: 2.1
Name: DocumentsReader
Version: 1.1.5
Summary: A package to read and process documents
Home-page: 
Author: Your Name
Author-email: your.email@example.com
License: MIT
Requires-Dist: WeasyPrint (==62.1)
Requires-Dist: Pillow (==10.1.0)
Requires-Dist: python-docx (==1.1.2)
Requires-Dist: python-pptx (==0.6.23)
Requires-Dist: openpyxl (==3.1.2)
Requires-Dist: pdf2image (==1.17.0)
Requires-Dist: torch (==2.1.2)
Requires-Dist: torchvision (==0.16.2)
Requires-Dist: transformers (==4.40.0)
Requires-Dist: sentencepiece (==0.1.99)
Requires-Dist: accelerate (==0.30.1)
Requires-Dist: bitsandbytes (==0.43.1)
